waldur_zabbix/__init__.py
waldur_zabbix/admin.py
waldur_zabbix/apps.py
waldur_zabbix/backend.py
waldur_zabbix/executors.py
waldur_zabbix/extension.py
waldur_zabbix/filters.py
waldur_zabbix/handlers.py
waldur_zabbix/managers.py
waldur_zabbix/models.py
waldur_zabbix/serializers.py
waldur_zabbix/tasks.py
waldur_zabbix/urls.py
waldur_zabbix/utils.py
waldur_zabbix/views.py
waldur_zabbix/migrations/0001_initial.py
waldur_zabbix/migrations/0002_add_trigger_priority.py
waldur_zabbix/migrations/__init__.py
waldur_zabbix/tests/__init__.py
waldur_zabbix/tests/factories.py
waldur_zabbix/tests/test_host.py
waldur_zabbix/tests/test_sla.py
waldur_zabbix/tests/test_trigger.py
waldur_zabbix/tests/test_utils.py
waldur_zabbix-0.8.4.dist-info/METADATA
waldur_zabbix-0.8.4.dist-info/RECORD
waldur_zabbix-0.8.4.dist-info/WHEEL
waldur_zabbix-0.8.4.dist-info/entry_points.txt
waldur_zabbix-0.8.4.dist-info/top_level.txt
