Metadata-Version: 2.1
Name: waldur-zabbix
Version: 0.8.4
Summary: Waldur Zabbix adds support for Zabbix monitoring server management
Home-page: http://waldur.com
Author: OpenNode Team
Author-email: info@opennodecloud.com
License: MIT
Platform: UNKNOWN
Classifier: Framework :: Django
Classifier: Intended Audience :: Developers
Classifier: Intended Audience :: System Administrators
Classifier: Operating System :: OS Independent
Classifier: License :: OSI Approved :: MIT License
Provides-Extra: dev
Requires-Dist: waldur-core (>=0.151.0)
Requires-Dist: pyzabbix (>=0.7.2)
Provides-Extra: dev
Requires-Dist: Sphinx (==1.2.2); extra == 'dev'
